[
    {
        "model": "rareapi.tag",
        "pk": 1,
        "fields": {
            "label": "fun"
        }
    },
    {
        "model": "rareapi.tag",
        "pk": 2,
        "fields": {
            "label": "snowflakes"
        }
    },
    {
        "model": "rareapi.tag",
        "pk": 3,
        "fields": {
            "label": "ice storm"
        }
    },
    {
        "model": "rareapi.tag",
        "pk": 4,
        "fields": {
            "label": "summer"
        }
    },
    {
        "model": "rareapi.tag",
        "pk": 5,
        "fields": {
            "label": "girlfriend"
        }
    }
]